simple_certmanager/__init__.py
simple_certmanager/admin.py
simple_certmanager/apps.py
simple_certmanager/constants.py
simple_certmanager/csr_generation.py
simple_certmanager/forms.py
simple_certmanager/mixins.py
simple_certmanager/models.py
simple_certmanager/py.typed
simple_certmanager/utils.py
simple_certmanager/validators.py
simple_certmanager/locale/nl/LC_MESSAGES/django.po
simple_certmanager/management/__init__.py
simple_certmanager/management/commands/__init__.py
simple_certmanager/management/commands/dump_certs.py
simple_certmanager/migrations/0001_initial.py
simple_certmanager/migrations/0002_alter_certificate_private_key_and_more.py
simple_certmanager/migrations/0003_signingrequest_and_more.py
simple_certmanager/migrations/0004_signingrequest_public_certificate.py
simple_certmanager/migrations/0005_remove_signingrequest_csr_and_private_key_must_be_set_together.py
simple_certmanager/migrations/0006_remove_signingrequest_csr.py
simple_certmanager/migrations/__init__.py
simple_certmanager/test/__init__.py
simple_certmanager/test/certificate_generation.py
simple_certmanager/test/factories.py
simple_certmanager/test/fixtures.py
simple_certmanager/test/plugin.py
simple_certmanager/test/data/README.md
simple_certmanager/test/data/test.certificate
simple_certmanager/test/data/test.key
django_simple_certmanager-2.4.1.dist-info/LICENSE
django_simple_certmanager-2.4.1.dist-info/METADATA
django_simple_certmanager-2.4.1.dist-info/WHEEL
django_simple_certmanager-2.4.1.dist-info/entry_points.txt
django_simple_certmanager-2.4.1.dist-info/top_level.txt
django_simple_certmanager-2.4.1.dist-info/RECORD
