Metadata-Version: 2.1
Name: django-simple-certmanager
Version: 2.4.1
Summary: Manage TLS certificates and keys in the Django admin
Author-email: Maykin Media <support@maykinmedia.nl>
License: Copyright 2022 Maykin Media
Project-URL: Homepage, https://github.com/maykinmedia/django-simple-certmanager
Project-URL: Documentation, http://django-simple-certmanager.readthedocs.io/en/latest/
Project-URL: Bug Tracker, https://github.com/maykinmedia/django-simple-certmanager/issues
Project-URL: Source Code, https://github.com/maykinmedia/django-simple-certmanager
Project-URL: Changelog, https://github.com/maykinmedia/django-simple-certmanager/blob/main/CHANGELOG.rst
Keywords: django,certificate,security
Classifier: Development Status :: 5 - Production/Stable
Classifier: Framework :: Django
Classifier: Framework :: Django :: 3.2
Classifier: Framework :: Django :: 4.2
Classifier: Intended Audience :: Developers
Classifier: Operating System :: Unix
Classifier: Operating System :: MacOS
Classifier: Operating System :: Microsoft :: Windows
Classifier: Programming Language :: Python :: 3.10
Classifier: Programming Language :: Python :: 3.11
Classifier: Programming Language :: Python :: 3.12
Classifier: Topic :: Software Development :: Libraries :: Python Modules
Requires-Python: >=3.10
License-File: LICENSE
Requires-Dist: django >=3.2
Requires-Dist: django-privates >=1.5
Requires-Dist: cryptography >=35.0.0
Provides-Extra: coverage
Requires-Dist: pytest-cov ; extra == 'coverage'
Provides-Extra: docs
Requires-Dist: sphinx ; extra == 'docs'
Requires-Dist: sphinx-rtd-theme ; extra == 'docs'
Provides-Extra: release
Requires-Dist: bump-my-version ; extra == 'release'
Provides-Extra: tests
Requires-Dist: pytest ; extra == 'tests'
Requires-Dist: pytest-django ; extra == 'tests'
Requires-Dist: pyquery ; extra == 'tests'
Requires-Dist: tox ; extra == 'tests'
Requires-Dist: isort ; extra == 'tests'
Requires-Dist: black ; extra == 'tests'
Requires-Dist: flake8 ; extra == 'tests'
Requires-Dist: freezegun ; extra == 'tests'
Provides-Extra: testutils
Requires-Dist: factory-boy ; extra == 'testutils'
Provides-Extra: type-checking
Requires-Dist: django-stubs[compatible-mypy] ; extra == 'type-checking'
